ptz_app/__init__.py
ptz_app/apps.py
ptz_app/functions/camera.py
ptz_app/migrations/0001_initial.py
ptz_app/migrations/0002_alter_preset_thumbnail.py
ptz_app/migrations/0003_remove_camerasettings_aperture_and_more.py
ptz_app/migrations/0004_remove_camerasettings_blue_gain_and_more.py
ptz_app/migrations/__init__.py
ptz_app/models.py
ptz_app/static/ptz_app/index.css
ptz_app/static/ptz_app/index.js
ptz_app/templates/ptz_app/camera.html
ptz_app/templates/ptz_app/index.html
ptz_app/templates/ptz_app/preset.html
ptz_app/urls.py
ptz_app/views/__init__.py
ptz_app/views/cameras.py
ptz_app/views/index.py
ptz_app/views/presets.py
ptz_control_app/__init__.py
ptz_control_app/main.py
ptz_project/__init__.py
ptz_project/asgi.py
ptz_project/settings.py
ptz_project/urls.py
ptz_project/wsgi.py
ptz_control_app-0.4.0.dist-info/METADATA
ptz_control_app-0.4.0.dist-info/WHEEL
ptz_control_app-0.4.0.dist-info/entry_points.txt
ptz_control_app-0.4.0.dist-info/RECORD
