Metadata-Version: 2.1
Name: ptz-control-app
Version: 0.4.0
Summary: Web app to control settings for PTZOptics cameras
License: MIT
Author: Nathan Collins
Author-email: nathantheinventor@gmail.com
Requires-Python: >=3.11,<4.0
Classifier: License :: OSI Approved :: MIT License
Classifier: Programming Language :: Python :: 3
Classifier: Programming Language :: Python :: 3.11
Classifier: Programming Language :: Python :: 3.12
Requires-Dist: Django (>=5.0.3,<6.0.0)
Requires-Dist: click (>=8.1.7,<9.0.0)
Requires-Dist: dacite (>=1.8.1,<2.0.0)
Requires-Dist: pillow (>=10.2.0,<11.0.0)
Requires-Dist: requests (>=2.31.0,<3.0.0)
